packages/__init__.py
packages/hyper_file.py
packages/hyper_suite.py
packages/hyper_utils.py
packages/tableau_server_utils.py
packages/time_decorator.py
parquet_to_hyper-1.1.4.dist-info/LICENSE
parquet_to_hyper-1.1.4.dist-info/METADATA
parquet_to_hyper-1.1.4.dist-info/WHEEL
parquet_to_hyper-1.1.4.dist-info/top_level.txt
parquet_to_hyper-1.1.4.dist-info/RECORD
