Metadata-Version: 2.1
Name: parquet-to-hyper
Version: 1.1.4
Summary: Create and publish tableau hyper files from parquet files.
Author-email: Guilherme Noronha <guilhermenoronha2001@gmail.com>
License: GNU GENERAL PUBLIC LICENSE
Project-URL: Homepage, https://github.com/guilhermenoronha/parquet-to-hyper
Project-URL: Bug Tracker, https://github.com/guilhermenoronha/parquet-to-hyper/issues
Keywords: Parquet,Tableau,Hyper,Extract
Classifier: Programming Language :: Python :: 3
Classifier: License :: OSI Approved :: GNU General Public License v3 (GPLv3)
Classifier: Operating System :: OS Independent
Requires-Python: >=3.9
License-File: LICENSE
Requires-Dist: tableauhyperapi <=0.0.17002
Requires-Dist: tableauserverclient <=0.24
Requires-Dist: pyarrow >=14.0.1
Provides-Extra: dev
Requires-Dist: pip-tools ; extra == 'dev'
Requires-Dist: pytest ; extra == 'dev'
Requires-Dist: bumpver ; extra == 'dev'
